nlpk/__init__.py
nlpk/nlpk_test.py
nlpk/lib/README.md
nlpk/lib/__init__.py
nlpk/lib/operator.cpython-35m-x86_64-linux-gnu.so
nlpk/lib/spam.cpython-35m-x86_64-linux-gnu.so
nlpk-0.0.6.dist-info/METADATA
nlpk-0.0.6.dist-info/RECORD
nlpk-0.0.6.dist-info/WHEEL
nlpk-0.0.6.dist-info/top_level.txt
