Metadata-Version: 2.1
Name: nlpk
Version: 0.0.6
Summary: Natural Language Processing for Korean
Home-page: UNKNOWN
Author: GyuHyeon Nam
Author-email: ngh3053@gmail.com
License: UNKNOWN
Keywords: nlp,korean
Platform: UNKNOWN
Classifier: Programming Language :: Python :: 3
Requires-Python: >=3
